{
  "$schema": "http://cyclonedx.org/schema/bom-1.4.schema.json",
  "bomFormat": "CycloneDX",
  "specVersion": "1.4",
  "serialNumber": "urn:uuid:c907c720-8a15-4392-97b3-8c8153617562",
  "version": 1,
  "metadata": {
    "timestamp": "2023-06-18T20:27:18.888112+00:00",
    "tools": [
      {
        "vendor": "CycloneDX",
        "name": "cyclonedx-bom",
        "version": "3.11.0"
      },
      {
        "vendor": "CycloneDX",
        "name": "cyclonedx-python-lib",
        "version": "3.1.1",
        "externalReferences": [
          {
            "url": "https://github.com/CycloneDX/cyclonedx-python-lib/actions",
            "type": "build-system"
          },
          {
            "url": "https://pypi.org/project/cyclonedx-python-lib/",
            "type": "distribution"
          },
          {
            "url": "https://cyclonedx.github.io/cyclonedx-python-lib/",
            "type": "documentation"
          },
          {
            "url": "https://github.com/CycloneDX/cyclonedx-python-lib/issues",
            "type": "issue-tracker"
          },
          {
            "url": "https://github.com/CycloneDX/cyclonedx-python-lib/blob/main/LICENSE",
            "type": "license"
          },
          {
            "url": "https://github.com/CycloneDX/cyclonedx-python-lib/blob/main/CHANGELOG.md",
            "type": "release-notes"
          },
          {
            "url": "https://github.com/CycloneDX/cyclonedx-python-lib",
            "type": "vcs"
          },
          {
            "url": "https://cyclonedx.org",
            "type": "website"
          }
        ]
      }
    ]
  },
  "components": [
    {
      "type": "library",
      "bom-ref": "623f8a14-7636-4811-8d9b-b0a1e1d65fce",
      "name": "atlassian-python-api",
      "version": "3.39.0",
      "purl": "pkg:pypi/atlassian-python-api@3.39.0"
    },
    {
      "type": "library",
      "bom-ref": "55dc0332-8c26-4e43-945e-1ee114844b26",
      "name": "jmespath",
      "version": "1.0.1",
      "purl": "pkg:pypi/jmespath@1.0.1"
    },
    {
      "type": "library",
      "bom-ref": "d9823042-98bb-4616-9750-1bae31c41db1",
      "name": "robotframework",
      "version": "6.1",
      "purl": "pkg:pypi/robotframework@6.1"
    },
    {
      "type": "library",
      "bom-ref": "cc81cd0d-87c7-4058-9120-9516cdca920d",
      "name": "wrapt",
      "version": "1.15.0",
      "purl": "pkg:pypi/wrapt@1.15.0"
    }
  ],
  "dependencies": [
    {
      "ref": "623f8a14-7636-4811-8d9b-b0a1e1d65fce",
      "dependsOn": []
    },
    {
      "ref": "55dc0332-8c26-4e43-945e-1ee114844b26",
      "dependsOn": []
    },
    {
      "ref": "d9823042-98bb-4616-9750-1bae31c41db1",
      "dependsOn": []
    },
    {
      "ref": "cc81cd0d-87c7-4058-9120-9516cdca920d",
      "dependsOn": []
    }
  ]
}
